{
  "version": 22,
  "languages": [
    0,
    1,
    2,
    3,
    4,
    5,
    6,
    7,
    8,
    9,
    10,
    11,
    12,
    13,
    14,
    15,
    16,
    17,
    18,
    19,
    20,
    21,
    22,
    23,
    24,
    25,
    26,
    27,
    28,
    29,
    30,
    31,
    32
  ],
  "attribute_headers": [],
  "entries": [
    {
      "name": "CH_Mes_Main_File_028_00",
      "guid": "085d13e5-2478-4d86-8324-86f835330878",
      "crc?": 3472617106,
      "hash": 915108173,
      "attributes": [],
      "content": [
        "執事の手記1",
        "Housekeeper's Memo 1",
        "Note de la gouvernante 1",
        "Nota della governante 1",
        "Notiz der Haushalterin",
        "Nota del ama de casa (1)",
        "Записка экономки 1",
        "Notatka gospodyni 1",
        "",
        "",
        "Bilhete da Criada 1",
        "집사의 수기 1",
        "女管家筆記1",
        "管家的笔记1",
        "",
        "",
        "",
        "",
        "",
        "",
        "",
        "مذكرة 1 لمدبرة المنزل",
        "",
        "",
        "",
        "",
        "",
        "",
        "",
        "",
        "",
        "",
        "Nota de la ama de casa (1)"
      ]
    },
    {
      "name": "CH_Mes_Main_File_028_01",
      "guid": "f6b93e02-6e33-420d-857d-2e76a5ee63c9",
      "crc?": 703752995,
      "hash": 186719358,
      "attributes": [],
      "content": [
        "私はとんだ不忠者にございます。\r\n\r\nご子息であるラモン様の\r\n歪んだ性格を正したいという\r\n貴方様の最後の願いを、\r\n私は叶えて差し上げることができませんでした。",
        "I have failed you, my lord.\r\n\r\nI was unable to fulfill your final commandment\r\nand keep the boy from the path of wickedness.",
        "J'ai échoué, mon seigneur.\r\n\r\nJe n'ai pas été capable d'exaucer votre dernier\r\nsouhait et de remettre le jeune garçon sur\r\nle droit chemin.",
        "Ho fallito, mio signore.\r\n\r\nNon sono stata in grado di adempiere al vostro\r\nultimo ordine, e mantenere il ragazzo lontano\r\ndal sentiero del male.",
        "Ich habe versagt, mein Herr.\r\n\r\nIch konnte Euren letzten Wunsch, den Jungen\r\nvom Pfad der Sündhaftigkeit abzubringen, nicht\r\nerfüllen.",
        "Le he fallado, señor mío.\r\n\r\nNo he sido capaz de cumplir con mi cometido final\r\nde mantener al chico lejos de los caminos del mal.",
        "Я подвела Вас, милорд.\r\n\r\nЯ не сумела исполнить Вашу последнюю волю\r\nи уберечь мальчика от греховного пути.",
        "Zawiodłam cię, mój panie.\r\n\r\nNie zdołałam wypełnić twojego ostatniego\r\nrozkazu i powstrzymać chłopca przed zejściem\r\nna drogę występku.",
        "",
        "",
        "Eu fui uma decepção, meu senhor.\r\n\r\nNão consegui realizar seu comando final de manter\r\no garoto longe do caminho da perversidade.",
        "저는 당신을 실망시켰습니다,\r\n주인님.\r\n\r\n마지막 명령을 이행하지 못했습니다.\r\n도련님이 사악한 길로 빠지는 것을\r\n막지 못했습니다.",
        "主人，我必須對你深表歉意。\r\n\r\n我沒法完成你的遺願，糾正拉蒙少爺頑劣的性格。",
        "主人，我让您失望了。\r\n\r\n我没能完成您的遗训，没能纠正那孩子，他\r\n还是走上了邪恶的路。",
        "",
        "",
        "",
        "",
        "",
        "",
        "",
        "لقد خذلتك يا سيدي.\r\n\r\nلم أتمكن من تنفيذ وصيتك الأخيرة\r\nوأبعد الصبي عن طريق الشر.",
        "",
        "",
        "",
        "",
        "",
        "",
        "",
        "",
        "",
        "",
        "Le fallé, señor mío.\r\n\r\nNo fui capaz de cumplir con mi cometido final\r\nde mantener al niño lejos de los caminos del mal."
      ]
    },
    {
      "name": "CH_Mes_Main_File_028_02",
      "guid": "695149b0-f78a-4926-a35f-47d7a5c47959",
      "crc?": 4270660869,
      "hash": 3949432535,
      "attributes": [],
      "content": [
        "その邪悪さの片鱗を最初に見たのは、\r\nまだラモン様が幼少の頃でした。\r\n\r\nラモン様は自らを“プルガルチト”と陰で呼んだ\r\nある給仕を自室に呼びつけました。\r\n\r\nすると、懐からおもむろに硫酸を取り出し、\r\n跪くそのものの顔にかけ始めたのです！",
        "I caught a glimpse of Master Ramón's evil\r\ntemperament during his younger years.\r\n\r\nWhen he discovered a servant mocked him by\r\nuttering \"Pulgarcito\" behind his back, he summoned\r\nher to his private chambers. After forcing her\r\nto kneel before him, Ramón doused her face with\r\na vial of vitriol he pulled out of his pocket!",
        "Maître Ramón n'était encore qu'un enfant quand\r\nj'ai vu pour la première fois le mal en lui.\r\n\r\nLorsqu'il découvrit qu'une servante se moquait\r\nde lui en l'appelant \"Pulgarcito\" dans son dos,\r\nil la convoqua dans ses appartements privés.\r\nAprès avoir forcé la jeune fille à se mettre à\r\ngenoux, il lui aspergea le visage avec un flacon\r\nde vitriol sorti de sa poche !",
        "Ho scorto il primo barlume di malvagità nel\r\npadrone Ramón quando era più giovane.\r\n\r\nUn giorno ha scoperto che una dei servitori\r\nlo prendeva in giro di nascosto chiamandolo\r\n\"Pulgarcito\", e l'ha convocata nelle sue stanze\r\nprivate. Dopo averla forzata a inginocchiarsi\r\ndinanzi a lui, Ramón ha tirato fuori dalla tasca\r\nuna fiala di acido solforico e gliel'ha schizzata\r\nsul volto!",
        "Bereits als er noch jung war, hatte ich einmal\r\nGelegenheit, einen kurzen Blick auf Ramóns\r\nböse Natur zu erhaschen.\r\n\r\nAls er herausfand, dass eine Dienerin ihn\r\nhinter seinem Rücken „Pulgarcito“ zu nennen\r\npflegte, rief er diese in seine Privatgemächer.\r\nEr befahl ihr, vor ihm auf die Knie zu gehen,\r\ndann zog er eine Flasche Vitriol aus seiner\r\nTasche und sprühte es ihr mitten ins Gesicht!",
        "Ya vi signos del mal temperamento del\r\nseñor Ramón en sus años mozos.\r\n\r\nCuando descubrió que una sirvienta se burló de él\r\nllamándole \"Pulgarcito\" a sus espaldas, la convocó\r\na sus aposentos. ¡Tras obligarla a arrodillarse\r\nante él, Ramón roció su rostro con un vial de\r\nveneno que llevaba en el bolsillo!",
        "Я замечала, что ещё в раннем детстве\r\nгосподин Рамон проявлял свою злую натуру.\r\n\r\nУзнав, что одна из служанок дала ему шутливое\r\nпрозвище Мальчик-с-пальчик, Рамон позвал её\r\nв свои покои, приказал ей встать на колени, вынул\r\nиз кармана флакон с серной кислотой и плеснул\r\nбедняге в лицо!",
        "Zauważyłam oznaki złego charakteru panicza\r\nRamona już w czasie jego młodości.\r\n\r\nKiedy odkrył, że służąca obraża go,\r\nnazywając go za plecami „Pulgarcito”, wezwał\r\nją do swoich prywatnych komnat. Tam zmusił\r\nją do uklęknięcia, po czym oblał jej twarz\r\nwyciągniętym z kieszeni witriolem!",
        "",
        "",
        "Notei o temperamento maligno do Mestre Ramón\r\ndurante sua juventude.\r\n\r\nQuando ele descobriu que uma criada zombou dele\r\ndizendo \"Pulgarcito\" pelas suas costas,\r\nchamou-a em seus aposentos privados. Depois de\r\nforçá-la a se ajoelhar, Ramón encharcou o rosto\r\ndela com um frasco de ácido sulfúrico que tirou\r\nde seu bolso!",
        "어린 라몬 님의 눈에서 그 사악한 기질을\r\n언뜻 보았습니다.\r\n하인이 뒤에서 자신을 \"풀가르시토\"라고\r\n부르며 놀린다는 것을 안 라몬 님은,\r\n그 하인을 자신의 방으로 부르셨습니다.\r\n그리고는 무릎을 꿇게 하시더니 주머니에서\r\n유황을 꺼내 하인의 얼굴에 부으시는 게\r\n아니겠습니까!",
        "我在少爺小時候已經察覺到有不妥。\r\n\r\n他發現有個女僕在背後說他是拇指仙童「普爾\r\n加西托」，他就把她帶到自己的房間，逼她跪下，\r\n還從口袋拿出硫酸潑向她的臉！",
        "在拉蒙少主小的时候，他恶魔般的坏脾气就\r\n已经初现苗头。\r\n\r\n有一次，少主发现一个仆人背地里嘲笑他为\r\n“普尔加西托”，便把她叫到自己的私房。强\r\n迫她跪在自己面前后，少主从口袋里掏出了\r\n一小瓶硫酸，浇在了她的脸上！",
        "",
        "",
        "",
        "",
        "",
        "",
        "",
        "لاحظت لمحة من الطبع الشرير\r\nللسيد رامون في سنوات شبابه.\r\n\r\nعندما اكتشف أن خادمة سخرت منه\r\nونعتته \"بعقلة الإصبع\" من وراء ظهره.\r\nاستدعاها إلى غرفته الخاصة\r\nوبعد إجبارها على الانحناء أمامه، أخرج رامون\r\nقارورة بها حمض الزاج من جيبه وغمر وجهها به!",
        "",
        "",
        "",
        "",
        "",
        "",
        "",
        "",
        "",
        "",
        "Ya vi signos del mal temperamento del\r\nseñor Ramón en sus años mozos.\r\n\r\nCuando descubrió que una sirvienta se burló de él\r\nllamándole \"Pulgarcito\" a sus espaldas, la convocó\r\na sus aposentos. ¡Tras obligarla a arrodillarse\r\nante él, Ramón roció su rostro con un vial de\r\nveneno que llevaba en el bolsillo!"
      ]
    },
    {
      "name": "CH_Mes_Main_File_028_03",
      "guid": "e44d9528-8c27-4098-8017-0fcbda26cd59",
      "crc?": 3683678566,
      "hash": 1168210231,
      "attributes": [],
      "content": [
        "皮膚が焼け爛れ、苦痛に身が歪む様を見る\r\n幼きラモン様のあの恍惚とした表情。\r\nいまだに私の脳裏に焼き付いております。\r\n\r\nそして時が経ち、ご両親を失い心を閉ざすラモン様に\r\n付け入るように、奴らはやってきたのです。\r\n\r\nあの忌々しい教団が――。",
        "The young master watched with glee when the\r\nservant writhed in agony as the skin melted from\r\nher face. His twisted grin still haunts my\r\ndreams to this very day.\r\n\r\nAs time passed, Ramón's treachery only deepened,\r\nand that infernal cult soon learned they could\r\nprey upon his vulnerable heart. Curse the fiends!",
        "Le jeune maître regarda avec satisfaction la\r\nservante se tordre de douleur alors que la peau\r\nde son visage tombait en lambeaux. Son rictus\r\nmalsain hante encore mes nuits.\r\n\r\nAvec le temps, la perfidie de Ramón n'a fait que\r\ncroître, et les membres de cette secte infernale\r\nse sont vite aperçus qu'ils pourraient exploiter\r\nson cœur vulnérable. Maudits soient-ils !",
        "Il giovane padrone fissava la donna con\r\nsoddisfazione, mentre lei si contorceva\r\nagonizzante e la pelle del suo viso si\r\nscioglieva. Ancora oggi quel suo ghigno\r\nmalefico appare nei miei peggiori incubi.\r\n\r\nCol passare del tempo, la perfidia di Ramón\r\nsi è fatta sempre più profonda, e quella setta\r\ninfernale ha capito di poter deviare il suo cuore\r\nvulnerabile. Che siano maledetti!",
        "Der junge Herr zeigte sich beim Anblick der Dienerin,\r\nwie sie sich vor Schmerzen wandte, während ihr\r\nGesicht sich von ihrem Schädel löste, voll der über-\r\nschwänglichen Freude. Sein irres Grinsen verfolgt\r\nmich bis zu diesem Tag.\r\n\r\nDie Zeit verging und sein heimtückisches Wesen\r\nverfestigte sich weiter, und dieser Kult verstand\r\nschnell, dass sein geschundenes Herz ein gefundenes\r\nFressen für sie war. Verdammnis den Feinden!",
        "El joven señor observó con una sonrisa cómo su\r\nsirvienta se retorcía de dolor mientras la piel de\r\nsu cara se derretía. Su malvada mueca aún se me\r\naparece en sueños.\r\n\r\nA medida que pasó el tiempo, la maldad de\r\nRamón no hizo más que acentuarse y ese culto\r\ninfernal no tardó en darse cuenta de que podría\r\ndevorar su vulnerable corazón. ¡Malditos demonios!",
        "Юный господин с удовольствием глядел, как слезает\r\nкожа с лица бьющейся в муках служанки. Его кривая\r\nухмылка даже спустя столько лет снится мне\r\nв кошмарах.\r\n\r\nС годами натура мальчика проявлялась всё сильнее,\r\nи вскоре эта дьявольская секта поняла, что может\r\nзавладеть его бедным сердцем. Проклятые негодяи!",
        "Młody panicz z zachwytem oglądał, jak służąca\r\nwije się z bólu, a kwas wyżera jej skórę.\r\nDo dziś dręczy mnie widok jego twarzy\r\nwykrzywionej w niegodziwym grymasie.\r\n\r\nWraz z wiekiem tkwiące w nim zło jeszcze się\r\npogłębiło, a ta piekielna sekta zobaczyła, że\r\nmoże żerować na jego podatnym sercu. Niech\r\nbędą przeklęte te demony!",
        "",
        "",
        "O jovem mestre observava satisfeito enquanto a\r\nserva se contorcia em agonia à medida que a pele\r\nderretia de seu rosto. Seu sorriso perverso\r\nassombra meus sonhos até hoje.\r\n\r\nCom o passar do tempo, a deslealdade de Ramón só\r\naumentou, e aquele culto infernal logo descobriu\r\nque poderia se aproveitar de seu coração\r\nvulnerável. Demônios malditos!",
        "얼굴 피부가 녹아내리는 고통으로 몸부림치는\r\n하인의 모습을 만족해하시며 보고 계셨습니다.\r\n라몬 님의 그 뒤틀린 웃음은 오늘까지도\r\n제 꿈에 나와 절 괴롭힙니다.\r\n\r\n날이 갈수록 라몬 님은 간악해지셨고, 극악한\r\n교단이 도련님의 연약한 마음을 이용할 수\r\n있다는 것을 안 것입니다. 악마 같은 놈들!",
        "少爺看著她的臉皮開肉綻，苦不堪言，竟然\r\n十分陶醉。那個邪惡的笑容，我到今天還\r\n記得一清二楚。\r\n\r\n隨時日過去，少爺的性格越來越扭曲，內心\r\n也越來越封閉，讓那個邪教有機可乘。該死\r\n的怪物！",
        "那个仆人脸上的皮肤慢慢地融化，身体因痛\r\n苦而剧烈地扭动。可少主却在那里咧着嘴笑，\r\n那扭曲的笑容，至今仍在我的梦里挥散不去。\r\n\r\n随着时间的推移，少主的叛逆愈发地加深，\r\n那个邪教组织很快发现，他们可以利用他脆\r\n弱的心灵。该死的魔鬼！",
        "",
        "",
        "",
        "",
        "",
        "",
        "",
        "ابتهج السيد الشاب وهو يراقب الخادمة تتلوى ألمًا\r\nبينما يذوب جلد وجهها. لا تزال ابتسامته المختلة\r\nتراودني في أحلامي حتى يومنا هذا.\r\n\r\nازداد غدر رامون بمرور الوقت،\r\nوسرعان ما علمت تلك الطائفة اللعينة\r\nأنها يمكنها أن تفترس قلبه الضعيف.\r\nاللعنة على هؤلاء الشياطين!",
        "",
        "",
        "",
        "",
        "",
        "",
        "",
        "",
        "",
        "",
        "El joven señor observó, con una sonrisa, cómo su\r\nsirvienta se retorcía de dolor mientras la piel de\r\nsu cara se derretía. Su malvada mueca aún se me\r\naparece en sueños.\r\n\r\nA medida que pasó el tiempo, la maldad de\r\nRamón no hizo más que acentuarse y, pronto, ese\r\nculto infernal se daría cuenta de que podía\r\ndevorar su vulnerable corazón. ¡Malditos demonios!"
      ]
    },
    {
      "name": "CH_Mes_Main_File_028_04",
      "guid": "b6b4dff3-bed8-4c25-b442-4ed33f13864d",
      "crc?": 1730423056,
      "hash": 272517667,
      "attributes": [],
      "content": [
        "あろうことか、代々サラザール家が封印してきた\r\n“プラーガ”を解き放ち、\r\nあまつさえ自らそれを受け入れるなど……！\r\n\r\nもはやラモン様は奴らの操り人形です。",
        "They've manipulated Master Ramón and turned\r\nhim into their puppet.\r\n\r\nWorst of all, they've managed to use him to\r\nunleash las plagas that the Salazar family has\r\nfought so long and hard to keep sealed away!",
        "Ils ont manipulé Maître Ramón et ont fait de lui\r\nleur marionnette.\r\n\r\nEt le pire dans tout cela, c'est qu'ils ont réussi\r\nà l'utiliser pour libérer les plagas que la famille\r\nSalazar avait juré de garder scellés à jamais !",
        "Hanno manipolato il padrone Ramón e lo hanno\r\nreso il loro burattino.\r\n\r\nE la cosa peggiore di tutte è che sono riusciti\r\na usarlo per scatenare las plagas, che la famiglia\r\nSalazar aveva combattuto così a lungo e duramente!",
        "Sie haben den jungen Herrn manipuliert und ihn\r\nzu ihrer Marionette gemacht.\r\n\r\nAm schlimmsten ist jedoch, dass sie es vollbracht\r\nhaben, ihn für die Entfesselung der Plaga zu\r\nbenutzen, welche die Familie Salazar so lange\r\nbekämpfte und sich so bemühte, für immer zu\r\nversiegeln.",
        "Han manipulado al señor Ramón y lo han convertido\r\nen su marioneta.\r\n\r\n¡Y lo peor de todo, le convencieron para que\r\nliberase las plagas que la familia Salazar había\r\ncontenido durante tanto tiempo!",
        "Они обманули господина Рамона и превратили его\r\nв свою марионетку.\r\n\r\nНо что ещё хуже, они выпустили лас плагас,\r\nкоторых род Салазаров так стремился\r\nудержать в заточении!",
        "Panicz Ramón został zmanipulowany i stał się\r\nich marionetką.\r\n\r\nCo gorsza, udało im się wykorzystać go\r\ndo uwolnienia las plagas, które rodzina Salazarów\r\ntak długo starała się trzymać w zamknięciu!",
        "",
        "",
        "Eles manipularam o Mestre Ramón e o\r\ntransformaram em seu fantoche.\r\n\r\nE pior de tudo, conseguiram usá-lo para\r\nlibertar las plagas que a família Salazar\r\ntanto se esforçou para\r\nmanter trancafiadas!",
        "그들은 라몬 님을 조종하더니 자신들의\r\n꼭두각시로 만들어 버렸습니다.\r\n\r\n무엇보다 살라자르 가문이 오랫동안\r\n투쟁하며 힘겹게 봉인해 온 플라가를\r\n라몬 님을 이용해 해방시켜 버렸습니다!",
        "拉蒙少爺被邪教的人操控，成了他們的提線人偶。\r\n\r\n他還把薩拉札家世世代代封印的普拉卡解放，\r\n更放進了自己體內！",
        "他们控制了拉蒙少主，把他变成了他们的傀\r\n儡。\r\n\r\n最糟糕的是，他们利用少主，把萨拉扎家族\r\n耗尽心血世世代代封印的普拉卡，也放了出\r\n来！",
        "",
        "",
        "",
        "",
        "",
        "",
        "",
        "تلاعبوا بعقل السيد رامون وحولوه لدمية تابعة لهم.\r\n\r\nالأسوأ من ذلك، أنهم تمكنوا من استغلاله لتحرير\r\nالبلاغا التي كافحتها عائلة سالازار لفترة طويلة\r\nوأبقوها حبيسة بصعوبة!",
        "",
        "",
        "",
        "",
        "",
        "",
        "",
        "",
        "",
        "",
        "Manipularon al señor Ramón y lo convirtieron\r\nen su marioneta.\r\n\r\n¡Y lo peor de todo, se las arreglaron para que\r\nliberase las plagas que la familia Salazar había\r\ncontenido durante tanto tiempo!"
      ]
    },
    {
      "name": "CH_Mes_Main_File_028_05",
      "guid": "5b39fd9a-05b3-4df6-903e-16d4b5c369a1",
      "crc?": 616496986,
      "hash": 1309700064,
      "attributes": [],
      "content": [
        "亡き先代、ディエゴ様。\r\n\r\n私はたとえこの身を堕とそうとも\r\n最期の時までラモン様と運命を共にする所存です。\r\n\r\nそれが、生まれたころよりお側に仕えてきた、\r\n執事である私の務めであり、\r\n貴方様への贖罪なのですから。",
        "Lord Diego,\r\n\r\nRest assured, I intend to watch over Master Ramón\r\nuntil the very end, whatever fate may befall us.\r\n\r\nAs a faithful servant of the Salazar family since\r\nbirth, it is my duty and my penance to you.",
        "Don Diego,\r\n\r\nRassurez-vous, j'ai l'intention de veiller sur\r\nMaître Ramón jusqu'au bout, quel que soit le sort\r\nqui nous est réservé.\r\n\r\nPour avoir été au service de la famille Salazar\r\ndepuis mon plus jeune âge, ceci est mon devoir\r\net ma pénitence.",
        "Lord Diego,\r\n\r\nLe garantisco che continuerò fino alla fine\r\na sorvegliare il padrone Ramón, qualunque sia\r\nil destino che ci attende.\r\n\r\nSono una fedele servitrice della famiglia Salazar\r\nfin dal giorno in cui sono nata, e questo è il mio\r\ndovere e la mia penitenza.",
        "Herr Diego,\r\n\r\nseid versichert, dass ich mein Lebtag über Herrn\r\nRamón wachen werde, welches Schicksal uns auch\r\nimmer ereilen mag.\r\n\r\nAls treue Dienerin der Familie Salazar seit meiner\r\nGeburt, ist es meine Pflicht und Buße Euch gegenüber.",
        "Don Diego,\r\n\r\nEsté tranquilo, pretendo cuidar del señor Ramón\r\nhasta el final, cualquiera que sea nuestro destino.\r\n\r\nComo fiel sirvienta de la familia Salazar desde su\r\nnacimiento, es mi deber y mi penitencia con usted.",
        "Владыка Диего!\r\n\r\nСмею заверить Вас, что я буду беречь\r\nгосподина Рамона до последней минуты жизни,\r\nкакая бы судьба ни постигла нас.\r\n\r\nЯ служу роду Салазаров со дня моего рождения.\r\nЯ выполню свой долг — пусть мне и нет прощения.",
        "Lordzie Diego,\r\n\r\nnie obawiaj się, gdyż zamierzam czuwać nad paniczem\r\nRamonem aż do końca, cokolwiek się wydarzy.\r\n\r\nJako lojalna sługa rodziny Salazarów od urodzenia,\r\npoczytuję to za mój obowiązek oraz zasłużoną pokutę.",
        "",
        "",
        "Senhor Diego,\r\n\r\nFique tranquilo, pretendo vigiar o Mestre Ramón\r\naté o fim, seja qual for o nosso destino.\r\n\r\nComo servo fiel da família Salazar desde o meu\r\nnascimento, é meu dever e penitência a vocês.",
        "디에고 님.\r\n\r\n어떤 운명이 닥치더라도 저는 제 숨이 다하는\r\n날까지 라몬 님을 보살필 것이니 안심하십시오.\r\n\r\n그것이 살라자르가의 충직한 하인으로 나고\r\n자란 저의 임무이자 주인님께 드리는 속죄입니다.",
        "迪亞哥大人：\r\n\r\n不論命運如何，我都會好好看顧拉蒙大人，\r\n直至最後一刻，所以請你好好放心。\r\n\r\n這是我出生以來一直侍奉薩拉札家的責任，\r\n也是我贖罪的唯一方法。",
        "迭戈大人，请您放心，不管前面有什么样的\r\n命运等着我，我都会履行照看拉蒙大人的职\r\n责直至生命最后一刻。\r\n\r\n生为萨拉扎家族忠实的仆人，这是我的天职，\r\n也是我向您赎罪的唯一方法。",
        "",
        "",
        "",
        "",
        "",
        "",
        "",
        "أيها السيد دييغو،\r\n\r\nكن مطمئنًا، فأنا أنوي الاعتناء بالسيد رامون\r\nحتى النهاية، مهما كان مصيرنا.\r\n\r\nبصفتي خادمة مخلصة لعائلة سالازار منذ صغري،\r\nفإن هذا واجبي وطريقة للتكفير عن ذنبي.",
        "",
        "",
        "",
        "",
        "",
        "",
        "",
        "",
        "",
        "",
        "Don Diego,\r\n\r\nEsté tranquilo, pretendo cuidar del señor Ramón\r\nhasta el final, cualquiera que sea nuestro destino.\r\n\r\nComo fiel sirvienta de la familia Salazar desde su\r\nnacimiento, es mi deber y mi penitencia con usted."
      ]
    },
    {
      "name": "CH_Mes_Main_File_028_06",
      "guid": "6ba66cb5-92e1-478c-91ec-88c33691d733",
      "crc?": 89028997,
      "hash": 2206809998,
      "attributes": [],
      "content": [
        "<END>",
        "<END>",
        "<END>",
        "<END>",
        "<END>",
        "<END>",
        "<END>",
        "<END>",
        "",
        "",
        "<END>",
        "<END>",
        "<END>",
        "<END>",
        "",
        "",
        "",
        "",
        "",
        "",
        "",
        "<END>",
        "",
        "",
        "",
        "",
        "",
        "",
        "",
        "",
        "",
        "",
        "<END>"
      ]
    }
  ]
}